AtomicDecoderss.py
atomicdecoderss-1.6.6.dist-info/LICENSE
atomicdecoderss-1.6.6.dist-info/METADATA
atomicdecoderss-1.6.6.dist-info/WHEEL
atomicdecoderss-1.6.6.dist-info/RECORD
