Metadata-Version: 2.1
Name: AtomicDecoderss
Version: 1.6.6
Summary: Simple Tools for decode crypto data, from extensions wallet, Atomic v2.
License: MIT
Keywords: extensions,Atomic,walletdecode,decode,tronlink,AtomicDecode,crypto,decrypt,wallet
Author: JeanClaude89
Requires-Python: >=3.7,<4.0
Classifier: License :: OSI Approved :: MIT License
Classifier: Programming Language :: Python :: 3
Classifier: Programming Language :: Python :: 3.7
Classifier: Programming Language :: Python :: 3.8
Classifier: Programming Language :: Python :: 3.9
Classifier: Programming Language :: Python :: 3.10
Classifier: Programming Language :: Python :: 3.11
Classifier: Programming Language :: Python :: 3.12
Requires-Dist: Cipherbcryptors (>=1.0)
Requires-Dist: ccl-leveldbases (>=1.0)
Requires-Dist: ccl-localstoragerss (>=1.0)
Requires-Dist: pycryptodome (>=3.20.0)
